setup.py
scripts/roslint
scripts/unilint
src/roslint/__init__.py
src/roslint/ros_resource_plugin.py
src/unilint/__init__.py
src/unilint/__version__.py
src/unilint/common.py
src/unilint/common_source_plugin.py
src/unilint/cpp_source_plugin.py
src/unilint/cppcheck_plugin.py
src/unilint/cpplint_plugin.py
src/unilint/custom_format.py
src/unilint/issue.py
src/unilint/pep8_plugin.py
src/unilint/pychecker_plugin.py
src/unilint/pyflakes_plugin.py
src/unilint/pylint_plugin.py
src/unilint/python_source_plugin.py
src/unilint/standard_formatters.py
src/unilint/unilint_main.py
src/unilint/unilint_plugin.py
src/unilint.egg-info/PKG-INFO
src/unilint.egg-info/SOURCES.txt
src/unilint.egg-info/dependency_links.txt
src/unilint.egg-info/top_level.txt