Metadata-Version: 1.0
Name: unilint
Version: 0.1.7
Summary: script wrapping static code analyzers producing unified output
Home-page: https://github.com/tkruse/unilint
Author: Thibault Kruse
Author-email: thibault.kruse@gmx.de
License: BSD
Download-URL: https://github.com/tkruse/unilint
Keywords: lint,python,pylint,pychecker,pyflakes,pep8,cppcheck,linux
Platform: UNKNOWN
Classifier: Programming Language :: Python
Classifier: License :: OSI Approved :: BSD License
